qda_package/MachineLogAnalytics.py
qda_package/ParentMachineInterface.py
qda_package/SystemInfo.py
qda_package/__init__.py
qda_package/pytransform/__init__.py
qda_package/pytransform/_pytransform.dll
qda_package/pytransform/_pytransform.so
qda_package_data/MachineLogAnalytics.py
qda_package_data/ParentMachineInterface.py
qda_package_data/SystemInfo.py
qda_package_data/__init__.py
qda_package_data/pytransform/__init__.py
qda_package_data/pytransform/_pytransform.dll
qda_package-1.0.2.dist-info/LICENSE
qda_package-1.0.2.dist-info/METADATA
qda_package-1.0.2.dist-info/WHEEL
qda_package-1.0.2.dist-info/top_level.txt
qda_package-1.0.2.dist-info/RECORD
