Metadata-Version: 2.1
Name: qda-package
Version: 1.0.2
Summary: An obfuscated Python package containing ParentInterface
Author: Hardik Kanak
Author-email: hardik.kanak@softqubes.com
Classifier: Programming Language :: Python :: 3
Classifier: License :: OSI Approved :: MIT License
Classifier: Operating System :: OS Independent
License-File: LICENSE
Requires-Dist: requests==2.31.0
Requires-Dist: psutil==6.0.0
Requires-Dist: GPUtil==1.4.0
